MANIFEST.in
setup.py
django_plus.egg-info/PKG-INFO
django_plus.egg-info/SOURCES.txt
django_plus.egg-info/dependency_links.txt
django_plus.egg-info/top_level.txt
djangoplus/__init__.py
djangoplus/admin.py
djangoplus/admin_utils.py
djangoplus/app_settings.py
djangoplus/cross_table.py
djangoplus/jinja_extensions.py
djangoplus/model_info.py
djangoplus/models.py
djangoplus/modify_models.py
djangoplus/test_utils.py
djangoplus/translation.py
djangoplus/fieldtypes/__init__.py
djangoplus/forms/__init__.py
djangoplus/management/__init__.py
djangoplus/management/commands/__init__.py
djangoplus/management/commands/reset_pg_sequences.py
djangoplus/management/commands/update_permissions.py
djangoplus/middleware/__init__.py
djangoplus/shortcuts/__init__.py
djangoplus/templates/admin/view_info.html
djangoplus/templates/admin/djangoplus/dynamictemplate/change_form.html
djangoplus/templates/djangoplus/ajaxfkwidget_window.html
djangoplus/templates/djangoplus/protectantirobots.html
djangoplus/templates/i18n_functions/admin_change_form.html
djangoplus/templates/i18n_functions/set_field_translation.html
djangoplus/templatetags/__init__.py
djangoplus/templatetags/djangoplus_tags.py
djangoplus/templatetags/i18n_functions.py
djangoplus/tests/__init__.py
djangoplus/urls/__init__.py
djangoplus/urls/i18n.py
djangoplus/utils/__init__.py
djangoplus/utils/decorators.py
djangoplus/utils/gmap_utils.py
djangoplus/utils/message_exception.py
djangoplus/views/__init__.py
djangoplus/views/i18n.py
djangoplus/widgets/__init__.py
djangoplus/widgets/ajax_fk_widget.py
djangoplus/widgets/ajax_m2m_widget.py
djangoplus/widgets/dropdown_multi_widget.py
djangoplus/widgets/jquery_auto_complete.py
djangoplus/widgets/raw_id_widget.py