Metadata-Version: 1.0
Name: django-plus
Version: 1.2.19
Summary: Django utilities library
Home-page: http://django-plus.googlecode.com
Author: Marinho Brandao
Author-email: marinho@gmail.com
License: GNU Lesser General Public License (LGPL)
Platform: UNKNOWN
